karyopyploter/__about__.py
karyopyploter/__init__.py
karyopyploter/constants.py
karyopyploter/grid.py
karyopyploter/ideogram.py
karyopyploter/utils.py
karyopyploter/static/cytobands_chm13.bed
karyopyploter/static/cytobands_hg19.bed
karyopyploter/static/cytobands_hg38.bed
karyopyploter-0.2.0.dist-info/METADATA
karyopyploter-0.2.0.dist-info/WHEEL
karyopyploter-0.2.0.dist-info/licenses/LICENSE
karyopyploter-0.2.0.dist-info/RECORD
