Metadata-Version: 2.4
Name: karyopyploter
Version: 0.2.0
Summary: Package to mimic the functionality of KaryoploteR, but in Python.
Project-URL: Documentation, https://github.com/vaslem/karyopyploter#readme
Project-URL: Issues, https://github.com/vaslem/karyopyploter/issues
Project-URL: Source, https://github.com/vaslem/karyopyploter
Author-email: vaslem <vaslemonidis@hotmail.com>
License-File: LICENSE
Classifier: Development Status :: 4 - Beta
Classifier: Intended Audience :: Science/Research
Classifier: License :: OSI Approved :: MIT License
Classifier: Natural Language :: English
Classifier: Operating System :: OS Independent
Classifier: Programming Language :: Python
Classifier: Programming Language :: Python :: 3.10
Classifier: Programming Language :: Python :: 3.11
Classifier: Programming Language :: Python :: Implementation :: CPython
Classifier: Programming Language :: Python :: Implementation :: PyPy
Classifier: Topic :: Scientific/Engineering :: Bio-Informatics
Requires-Python: >=3.10
Requires-Dist: matplotlib>=3.0.0
Requires-Dist: numpy>=2.0.0
Requires-Dist: pandas>=2.0.0
Requires-Dist: typeguard>=4.0.0
Provides-Extra: dev
Requires-Dist: black>=23.1.0; extra == 'dev'
Requires-Dist: coverage[toml]>=6.5; extra == 'dev'
Requires-Dist: isort; extra == 'dev'
Requires-Dist: mypy>=1.0.0; extra == 'dev'
Requires-Dist: pre-commit; extra == 'dev'
Requires-Dist: pytest; extra == 'dev'
Requires-Dist: ruff>=0.0.243; extra == 'dev'
